Workbook

Sheet Lisez-moi
A1: Artaluz — Grille tarifaire à compléter
A3: Remplissez uniquement les cellules jaunes (Prix HT, suppléments HT).
A4: Les prix TTC et les surfaces se calculent automatiquement.
A5: Les formats sont une proposition : ajoutez, supprimez ou modifiez des lignes librement.
A6: Le taux de TVA est réglable dans l'onglet Paramètres (20 % par défaut, hypothèse France).
A8: Exemple de saisie (fictif) :
A9: Bâche 200 × 100 cm → Prix HT : 89,00 → Prix TTC calculé : 106,80

Sheet Produits
A1: Réf | B1: Support | C1: Format | D1: Largeur (cm) | E1: Hauteur (cm) | F1: Surface (m²) | G1: PRHT | H1: Coeff Marge | I1: Prix HT (€) | J1: Prix TTC (€) | K1: Commission artiste | L1: Marge Artaluz | M1: Marge en % | N1: Remarques | O1: Prix TTC final (€) | P1: Prix HT final (€) | Q1: Commission artiste finale (€) | R1: Qté minimum
A2: BAC-01 | B2: Bâche qualité éco | C2: 100 × 50 cm | D2: 100 | E2: 50 | F2: =D2*E2/10000 -> 0.5 | G2: =(F2*1.2*1.76+F2*1.28) -> 1.696 | H2: 15 | I2: =G2*H2 -> 25.44 | J2: =IF(I2="","",I2*(1+Paramètres!$B$2)) -> 30.528 | K2: =I2*0.1 -> 2.544 | L2: =I2-K2-G2 -> 21.2 | M2: =L2/I2 -> 0.83333333 | O2: =IF(J2="","",ROUNDUP(J2+0.01,0)-0.01) -> 30.99 | P2: =IF(O2="","",O2/(1+Paramètres!$B$2)) -> 25.825 | Q2: =IF(P2="","",P2*0.1) -> 2.5825 | R2: 1
A3: BAC-02 | B3: Bâche qualité éco | C3: 150 × 50 cm | D3: 150 | E3: 50 | F3: =D3*E3/10000 -> 0.75 | G3: =(F3*1.2*1.76+F3*1.28) -> 2.544 | H3: =H2 -> 15 | I3: =G3*H3 -> 38.16 | J3: =IF(I3="","",I3*(1+Paramètres!$B$2)) -> 45.792 | K3: =I3*0.1 -> 3.816 | L3: =I3-K3-G3 -> 31.8 | M3: =L3/I3 -> 0.83333333 | O3: =IF(J3="","",ROUNDUP(J3+0.01,0)-0.01) -> 45.99 | P3: =IF(O3="","",O3/(1+Paramètres!$B$2)) -> 38.325 | Q3: =IF(P3="","",P3*0.1) -> 3.8325 | R3: 1
A4: BAC-03 | B4: Bâche qualité éco | C4: 200 × 50 cm | D4: 200 | E4: 50 | F4: =D4*E4/10000 -> 1 | G4: =(F4*1.2*1.76+F4*1.28) -> 3.392 | H4: =H3 -> 15 | I4: =G4*H4 -> 50.88 | J4: =IF(I4="","",I4*(1+Paramètres!$B$2)) -> 61.056 | K4: =I4*0.1 -> 5.088 | L4: =I4-K4-G4 -> 42.4 | M4: =L4/I4 -> 0.83333333 | O4: =IF(J4="","",ROUNDUP(J4+0.01,0)-0.01) -> 61.99 | P4: =IF(O4="","",O4/(1+Paramètres!$B$2)) -> 51.658333 | Q4: =IF(P4="","",P4*0.1) -> 5.1658333 | R4: 1
A5: BAC-04 | B5: Bâche qualité éco | C5: 100 × 100 cm | D5: 100 | E5: 100 | F5: =D5*E5/10000 -> 1 | G5: =(F5*1.2*1.76+F5*1.28) -> 3.392 | H5: =H4 -> 15 | I5: =G5*H5 -> 50.88 | J5: =IF(I5="","",I5*(1+Paramètres!$B$2)) -> 61.056 | K5: =I5*0.1 -> 5.088 | L5: =I5-K5-G5 -> 42.4 | M5: =L5/I5 -> 0.83333333 | O5: =IF(J5="","",ROUNDUP(J5+0.01,0)-0.01) -> 61.99 | P5: =IF(O5="","",O5/(1+Paramètres!$B$2)) -> 51.658333 | Q5: =IF(P5="","",P5*0.1) -> 5.1658333 | R5: 1
A6: BAC-05 | B6: Bâche qualité éco | C6: 150 × 100 cm | D6: 150 | E6: 100 | F6: =D6*E6/10000 -> 1.5 | G6: =(F6*1.2*1.76+F6*1.28) -> 5.088 | H6: =H5 -> 15 | I6: =G6*H6 -> 76.32 | J6: =IF(I6="","",I6*(1+Paramètres!$B$2)) -> 91.584 | K6: =I6*0.1 -> 7.632 | L6: =I6-K6-G6 -> 63.6 | M6: =L6/I6 -> 0.83333333 | O6: =IF(J6="","",ROUNDUP(J6+0.01,0)-0.01) -> 91.99 | P6: =IF(O6="","",O6/(1+Paramètres!$B$2)) -> 76.658333 | Q6: =IF(P6="","",P6*0.1) -> 7.6658333 | R6: 1
A7: BAC-06 | B7: Bâche qualité éco | C7: 200 × 100 cm | D7: 200 | E7: 100 | F7: =D7*E7/10000 -> 2 | G7: =(F7*1.2*1.76+F7*1.28) -> 6.784 | H7: =H6 -> 15 | I7: =G7*H7 -> 101.76 | J7: =IF(I7="","",I7*(1+Paramètres!$B$2)) -> 122.112 | K7: =I7*0.1 -> 10.176 | L7: =I7-K7-G7 -> 84.8 | M7: =L7/I7 -> 0.83333333 | O7: =IF(J7="","",ROUNDUP(J7+0.01,0)-0.01) -> 122.99 | P7: =IF(O7="","",O7/(1+Paramètres!$B$2)) -> 102.49167 | Q7: =IF(P7="","",P7*0.1) -> 10.249167 | R7: 1
A8: BAC-07 | B8: Bâche qualité éco | C8: 250 × 100 cm | D8: 250 | E8: 100 | F8: =D8*E8/10000 -> 2.5 | G8: =(F8*1.2*1.76+F8*1.28) -> 8.48 | H8: =H7 -> 15 | I8: =G8*H8 -> 127.2 | J8: =IF(I8="","",I8*(1+Paramètres!$B$2)) -> 152.64 | K8: =I8*0.1 -> 12.72 | L8: =I8-K8-G8 -> 106 | M8: =L8/I8 -> 0.83333333 | O8: =IF(J8="","",ROUNDUP(J8+0.01,0)-0.01) -> 152.99 | P8: =IF(O8="","",O8/(1+Paramètres!$B$2)) -> 127.49167 | Q8: =IF(P8="","",P8*0.1) -> 12.749167 | R8: 1
A9: BAC-08 | B9: Bâche qualité éco | C9: 300 × 100 cm | D9: 300 | E9: 100 | F9: =D9*E9/10000 -> 3 | G9: =(F9*1.2*1.76+F9*1.28) -> 10.176 | H9: =H8 -> 15 | I9: =G9*H9 -> 152.64 | J9: =IF(I9="","",I9*(1+Paramètres!$B$2)) -> 183.168 | K9: =I9*0.1 -> 15.264 | L9: =I9-K9-G9 -> 127.2 | M9: =L9/I9 -> 0.83333333 | O9: =IF(J9="","",ROUNDUP(J9+0.01,0)-0.01) -> 183.99 | P9: =IF(O9="","",O9/(1+Paramètres!$B$2)) -> 153.325 | Q9: =IF(P9="","",P9*0.1) -> 15.3325 | R9: 1
A10: BAC-09 | B10: Bâche qualité éco | C10: 100 × 130 cm | D10: 100 | E10: 130 | F10: =D10*E10/10000 -> 1.3 | G10: =(F10*1.2*1.76+F10*1.28) -> 4.4096 | H10: =H9 -> 15 | I10: =G10*H10 -> 66.144 | J10: =IF(I10="","",I10*(1+Paramètres!$B$2)) -> 79.3728 | K10: =I10*0.1 -> 6.6144 | L10: =I10-K10-G10 -> 55.12 | M10: =L10/I10 -> 0.83333333 | O10: =IF(J10="","",ROUNDUP(J10+0.01,0)-0.01) -> 79.99 | P10: =IF(O10="","",O10/(1+Paramètres!$B$2)) -> 66.658333 | Q10: =IF(P10="","",P10*0.1) -> 6.6658333 | R10: 1
A11: BAC-10 | B11: Bâche qualité éco | C11: 150 × 130 cm | D11: 150 | E11: 130 | F11: =D11*E11/10000 -> 1.95 | G11: =(F11*1.2*1.76+F11*1.28) -> 6.6144 | H11: =H10 -> 15 | I11: =G11*H11 -> 99.216 | J11: =IF(I11="","",I11*(1+Paramètres!$B$2)) -> 119.0592 | K11: =I11*0.1 -> 9.9216 | L11: =I11-K11-G11 -> 82.68 | M11: =L11/I11 -> 0.83333333 | O11: =IF(J11="","",ROUNDUP(J11+0.01,0)-0.01) -> 119.99 | P11: =IF(O11="","",O11/(1+Paramètres!$B$2)) -> 99.991667 | Q11: =IF(P11="","",P11*0.1) -> 9.9991667 | R11: 1
A12: BAC-11 | B12: Bâche qualité éco | C12: 200 × 130 cm | D12: 200 | E12: 130 | F12: =D12*E12/10000 -> 2.6 | G12: =(F12*1.2*1.76+F12*1.28) -> 8.8192 | H12: =H11 -> 15 | I12: =G12*H12 -> 132.288 | J12: =IF(I12="","",I12*(1+Paramètres!$B$2)) -> 158.7456 | K12: =I12*0.1 -> 13.2288 | L12: =I12-K12-G12 -> 110.24 | M12: =L12/I12 -> 0.83333333 | O12: =IF(J12="","",ROUNDUP(J12+0.01,0)-0.01) -> 158.99 | P12: =IF(O12="","",O12/(1+Paramètres!$B$2)) -> 132.49167 | Q12: =IF(P12="","",P12*0.1) -> 13.249167 | R12: 1
A13: BAC-12 | B13: Bâche qualité éco | C13: 250 × 130 cm | D13: 250 | E13: 130 | F13: =D13*E13/10000 -> 3.25 | G13: =(F13*1.2*1.76+F13*1.28) -> 11.024 | H13: =H12 -> 15 | I13: =G13*H13 -> 165.36 | J13: =IF(I13="","",I13*(1+Paramètres!$B$2)) -> 198.432 | K13: =I13*0.1 -> 16.536 | L13: =I13-K13-G13 -> 137.8 | M13: =L13/I13 -> 0.83333333 | O13: =IF(J13="","",ROUNDUP(J13+0.01,0)-0.01) -> 198.99 | P13: =IF(O13="","",O13/(1+Paramètres!$B$2)) -> 165.825 | Q13: =IF(P13="","",P13*0.1) -> 16.5825 | R13: 1
A14: BAC-13 | B14: Bâche qualité éco | C14: 300 × 130 cm | D14: 300 | E14: 130 | F14: =D14*E14/10000 -> 3.9 | G14: =(F14*1.2*1.76+F14*1.28) -> 13.2288 | H14: =H13 -> 15 | I14: =G14*H14 -> 198.432 | J14: =IF(I14="","",I14*(1+Paramètres!$B$2)) -> 238.1184 | K14: =I14*0.1 -> 19.8432 | L14: =I14-K14-G14 -> 165.36 | M14: =L14/I14 -> 0.83333333 | O14: =IF(J14="","",ROUNDUP(J14+0.01,0)-0.01) -> 238.99 | P14: =IF(O14="","",O14/(1+Paramètres!$B$2)) -> 199.15833 | Q14: =IF(P14="","",P14*0.1) -> 19.915833 | R14: 1
... A18: BAC-17 | B18: Bâche qualité éco | C18: 300 × 150 cm | D18: 300 | E18: 150 | F18: =D18*E18/10000 -> 4.5 | G18: =(F18*1.2*1.76+F18*1.28) -> 15.264 | H18: =H17 -> 15 | I18: =G18*H18 -> 228.96 | J18: =IF(I18="","",I18*(1+Paramètres!$B$2)) -> 274.752 | K18: =I18*0.1 -> 22.896 | L18: =I18-K18-G18 -> 190.8 | M18: =L18/I18 -> 0.83333333 | O18: =IF(J18="","",ROUNDUP(J18+0.01,0)-0.01) -> 274.99 | P18: =IF(O18="","",O18/(1+Paramètres!$B$2)) -> 229.15833 | Q18: =IF(P18="","",P18*0.1) -> 22.915833 | R18: 1
A19: BAC-18 | B19: Bâche qualité standard | C19: 100 × 50 cm | D19: 100 | E19: 50 | F19: =D19*E19/10000 -> 0.5 | G19: =(F19*1.2*2.4+F19*1.28) -> 2.08 | H19: =H18 -> 15 | I19: =G19*H19 -> 31.2 | J19: =IF(I19="","",I19*(1+Paramètres!$B$2)) -> 37.44 | K19: =I19*0.1 -> 3.12 | L19: =I19-K19-G19 -> 26 | M19: =L19/I19 -> 0.83333333 | O19: =IF(J19="","",ROUNDUP(J19+0.01,0)-0.01) -> 37.99 | P19: =IF(O19="","",O19/(1+Paramètres!$B$2)) -> 31.658333 | Q19: =IF(P19="","",P19*0.1) -> 3.1658333 | R19: 1
A20: BAC-19 | B20: Bâche qualité standard | C20: 150 × 50 cm | D20: 150 | E20: 50 | F20: =D20*E20/10000 -> 0.75 | G20: =(F20*1.2*2.4+F20*1.28) -> 3.12 | H20: =H19 -> 15 | I20: =G20*H20 -> 46.8 | J20: =IF(I20="","",I20*(1+Paramètres!$B$2)) -> 56.16 | K20: =I20*0.1 -> 4.68 | L20: =I20-K20-G20 -> 39 | M20: =L20/I20 -> 0.83333333 | O20: =IF(J20="","",ROUNDUP(J20+0.01,0)-0.01) -> 56.99 | P20: =IF(O20="","",O20/(1+Paramètres!$B$2)) -> 47.491667 | Q20: =IF(P20="","",P20*0.1) -> 4.7491667 | R20: 1
A21: BAC-20 | B21: Bâche qualité standard | C21: 200 × 50 cm | D21: 200 | E21: 50 | F21: =D21*E21/10000 -> 1 | G21: =(F21*1.2*2.4+F21*1.28) -> 4.16 | H21: =H20 -> 15 | I21: =G21*H21 -> 62.4 | J21: =IF(I21="","",I21*(1+Paramètres!$B$2)) -> 74.88 | K21: =I21*0.1 -> 6.24 | L21: =I21-K21-G21 -> 52 | M21: =L21/I21 -> 0.83333333 | O21: =IF(J21="","",ROUNDUP(J21+0.01,0)-0.01) -> 74.99 | P21: =IF(O21="","",O21/(1+Paramètres!$B$2)) -> 62.491667 | Q21: =IF(P21="","",P21*0.1) -> 6.2491667 | R21: 1
A22: BAC-21 | B22: Bâche qualité standard | C22: 100 × 100 cm | D22: 100 | E22: 100 | F22: =D22*E22/10000 -> 1 | G22: =(F22*1.2*2.4+F22*1.28) -> 4.16 | H22: =H21 -> 15 | I22: =G22*H22 -> 62.4 | J22: =IF(I22="","",I22*(1+Paramètres!$B$2)) -> 74.88 | K22: =I22*0.1 -> 6.24 | L22: =I22-K22-G22 -> 52 | M22: =L22/I22 -> 0.83333333 | O22: =IF(J22="","",ROUNDUP(J22+0.01,0)-0.01) -> 74.99 | P22: =IF(O22="","",O22/(1+Paramètres!$B$2)) -> 62.491667 | Q22: =IF(P22="","",P22*0.1) -> 6.2491667 | R22: 1
A23: BAC-22 | B23: Bâche qualité standard | C23: 150 × 100 cm | D23: 150 | E23: 100 | F23: =D23*E23/10000 -> 1.5 | G23: =(F23*1.2*2.4+F23*1.28) -> 6.24 | H23: =H22 -> 15 | I23: =G23*H23 -> 93.6 | J23: =IF(I23="","",I23*(1+Paramètres!$B$2)) -> 112.32 | K23: =I23*0.1 -> 9.36 | L23: =I23-K23-G23 -> 78 | M23: =L23/I23 -> 0.83333333 | O23: =IF(J23="","",ROUNDUP(J23+0.01,0)-0.01) -> 112.99 | P23: =IF(O23="","",O23/(1+Paramètres!$B$2)) -> 94.158333 | Q23: =IF(P23="","",P23*0.1) -> 9.4158333 | R23: 1
A24: BAC-23 | B24: Bâche qualité standard | C24: 200 × 100 cm | D24: 200 | E24: 100 | F24: =D24*E24/10000 -> 2 | G24: =(F24*1.2*2.4+F24*1.28) -> 8.32 | H24: =H23 -> 15 | I24: =G24*H24 -> 124.8 | J24: =IF(I24="","",I24*(1+Paramètres!$B$2)) -> 149.76 | K24: =I24*0.1 -> 12.48 | L24: =I24-K24-G24 -> 104 | M24: =L24/I24 -> 0.83333333 | O24: =IF(J24="","",ROUNDUP(J24+0.01,0)-0.01) -> 149.99 | P24: =IF(O24="","",O24/(1+Paramètres!$B$2)) -> 124.99167 | Q24: =IF(P24="","",P24*0.1) -> 12.499167 | R24: 1
A25: BAC-24 | B25: Bâche qualité standard | C25: 250 × 100 cm | D25: 250 | E25: 100 | F25: =D25*E25/10000 -> 2.5 | G25: =(F25*1.2*2.4+F25*1.28) -> 10.4 | H25: =H24 -> 15 | I25: =G25*H25 -> 156 | J25: =IF(I25="","",I25*(1+Paramètres!$B$2)) -> 187.2 | K25: =I25*0.1 -> 15.6 | L25: =I25-K25-G25 -> 130 | M25: =L25/I25 -> 0.83333333 | O25: =IF(J25="","",ROUNDUP(J25+0.01,0)-0.01) -> 187.99 | P25: =IF(O25="","",O25/(1+Paramètres!$B$2)) -> 156.65833 | Q25: =IF(P25="","",P25*0.1) -> 15.665833 | R25: 1
A26: BAC-25 | B26: Bâche qualité standard | C26: 300 × 100 cm | D26: 300 | E26: 100 | F26: =D26*E26/10000 -> 3 | G26: =(F26*1.2*2.4+F26*1.28) -> 12.48 | H26: =H25 -> 15 | I26: =G26*H26 -> 187.2 | J26: =IF(I26="","",I26*(1+Paramètres!$B$2)) -> 224.64 | K26: =I26*0.1 -> 18.72 | L26: =I26-K26-G26 -> 156 | M26: =L26/I26 -> 0.83333333 | O26: =IF(J26="","",ROUNDUP(J26+0.01,0)-0.01) -> 224.99 | P26: =IF(O26="","",O26/(1+Paramètres!$B$2)) -> 187.49167 | Q26: =IF(P26="","",P26*0.1) -> 18.749167 | R26: 1
A27: BAC-26 | B27: Bâche qualité standard | C27: 100 × 130 cm | D27: 100 | E27: 130 | F27: =D27*E27/10000 -> 1.3 | G27: =(F27*1.2*2.4+F27*1.28) -> 5.408 | H27: =H26 -> 15 | I27: =G27*H27 -> 81.12 | J27: =IF(I27="","",I27*(1+Paramètres!$B$2)) -> 97.344 | K27: =I27*0.1 -> 8.112 | L27: =I27-K27-G27 -> 67.6 | M27: =L27/I27 -> 0.83333333 | O27: =IF(J27="","",ROUNDUP(J27+0.01,0)-0.01) -> 97.99 | P27: =IF(O27="","",O27/(1+Paramètres!$B$2)) -> 81.658333 | Q27: =IF(P27="","",P27*0.1) -> 8.1658333 | R27: 1
A28: BAC-27 | B28: Bâche qualité standard | C28: 150 × 130 cm | D28: 150 | E28: 130 | F28: =D28*E28/10000 -> 1.95 | G28: =(F28*1.2*2.4+F28*1.28) -> 8.112 | H28: =H27 -> 15 | I28: =G28*H28 -> 121.68 | J28: =IF(I28="","",I28*(1+Paramètres!$B$2)) -> 146.016 | K28: =I28*0.1 -> 12.168 | L28: =I28-K28-G28 -> 101.4 | M28: =L28/I28 -> 0.83333333 | O28: =IF(J28="","",ROUNDUP(J28+0.01,0)-0.01) -> 146.99 | P28: =IF(O28="","",O28/(1+Paramètres!$B$2)) -> 122.49167 | Q28: =IF(P28="","",P28*0.1) -> 12.249167 | R28: 1
A29: BAC-28 | B29: Bâche qualité standard | C29: 200 × 130 cm | D29: 200 | E29: 130 | F29: =D29*E29/10000 -> 2.6 | G29: =(F29*1.2*2.4+F29*1.28) -> 10.816 | H29: =H28 -> 15 | I29: =G29*H29 -> 162.24 | J29: =IF(I29="","",I29*(1+Paramètres!$B$2)) -> 194.688 | K29: =I29*0.1 -> 16.224 | L29: =I29-K29-G29 -> 135.2 | M29: =L29/I29 -> 0.83333333 | O29: =IF(J29="","",ROUNDUP(J29+0.01,0)-0.01) -> 194.99 | P29: =IF(O29="","",O29/(1+Paramètres!$B$2)) -> 162.49167 | Q29: =IF(P29="","",P29*0.1) -> 16.249167 | R29: 1
A30: BAC-29 | B30: Bâche qualité standard | C30: 250 × 130 cm | D30: 250 | E30: 130 | F30: =D30*E30/10000 -> 3.25 | G30: =(F30*1.2*2.4+F30*1.28) -> 13.52 | H30: =H29 -> 15 | I30: =G30*H30 -> 202.8 | J30: =IF(I30="","",I30*(1+Paramètres!$B$2)) -> 243.36 | K30: =I30*0.1 -> 20.28 | L30: =I30-K30-G30 -> 169 | M30: =L30/I30 -> 0.83333333 | O30: =IF(J30="","",ROUNDUP(J30+0.01,0)-0.01) -> 243.99 | P30: =IF(O30="","",O30/(1+Paramètres!$B$2)) -> 203.325 | Q30: =IF(P30="","",P30*0.1) -> 20.3325 | R30: 1
... A35: BAC-34 | B35: Bâche qualité standard | C35: 300 × 150 cm | D35: 300 | E35: 150 | F35: =D35*E35/10000 -> 4.5 | G35: =(F35*1.2*2.4+F35*1.28) -> 18.72 | H35: =H34 -> 15 | I35: =G35*H35 -> 280.8 | J35: =IF(I35="","",I35*(1+Paramètres!$B$2)) -> 336.96 | K35: =I35*0.1 -> 28.08 | L35: =I35-K35-G35 -> 234 | M35: =L35/I35 -> 0.83333333 | O35: =IF(J35="","",ROUNDUP(J35+0.01,0)-0.01) -> 336.99 | P35: =IF(O35="","",O35/(1+Paramètres!$B$2)) -> 280.825 | Q35: =IF(P35="","",P35*0.1) -> 28.0825 | R35: 1
A36: BAC-35 | B36: Bâche qualité supérieure | C36: 100 × 50 cm | D36: 100 | E36: 50 | F36: =D36*E36/10000 -> 0.5 | G36: =(F36*1.2*4.24+F36*1.28) -> 3.184 | H36: =H35 -> 15 | I36: =G36*H36 -> 47.76 | J36: =IF(I36="","",I36*(1+Paramètres!$B$2)) -> 57.312 | K36: =I36*0.1 -> 4.776 | L36: =I36-K36-G36 -> 39.8 | M36: =L36/I36 -> 0.83333333 | O36: =IF(J36="","",ROUNDUP(J36+0.01,0)-0.01) -> 57.99 | P36: =IF(O36="","",O36/(1+Paramètres!$B$2)) -> 48.325 | Q36: =IF(P36="","",P36*0.1) -> 4.8325 | R36: 1
A37: BAC-36 | B37: Bâche qualité supérieure | C37: 150 × 50 cm | D37: 150 | E37: 50 | F37: =D37*E37/10000 -> 0.75 | G37: =(F37*1.2*4.24+F37*1.28) -> 4.776 | H37: =H36 -> 15 | I37: =G37*H37 -> 71.64 | J37: =IF(I37="","",I37*(1+Paramètres!$B$2)) -> 85.968 | K37: =I37*0.1 -> 7.164 | L37: =I37-K37-G37 -> 59.7 | M37: =L37/I37 -> 0.83333333 | O37: =IF(J37="","",ROUNDUP(J37+0.01,0)-0.01) -> 85.99 | P37: =IF(O37="","",O37/(1+Paramètres!$B$2)) -> 71.658333 | Q37: =IF(P37="","",P37*0.1) -> 7.1658333 | R37: 1
A38: BAC-37 | B38: Bâche qualité supérieure | C38: 200 × 50 cm | D38: 200 | E38: 50 | F38: =D38*E38/10000 -> 1 | G38: =(F38*1.2*4.24+F38*1.28) -> 6.368 | H38: =H37 -> 15 | I38: =G38*H38 -> 95.52 | J38: =IF(I38="","",I38*(1+Paramètres!$B$2)) -> 114.624 | K38: =I38*0.1 -> 9.552 | L38: =I38-K38-G38 -> 79.6 | M38: =L38/I38 -> 0.83333333 | O38: =IF(J38="","",ROUNDUP(J38+0.01,0)-0.01) -> 114.99 | P38: =IF(O38="","",O38/(1+Paramètres!$B$2)) -> 95.825 | Q38: =IF(P38="","",P38*0.1) -> 9.5825 | R38: 1
A39: BAC-38 | B39: Bâche qualité supérieure | C39: 100 × 100 cm | D39: 100 | E39: 100 | F39: =D39*E39/10000 -> 1 | G39: =(F39*1.2*4.24+F39*1.28) -> 6.368 | H39: =H38 -> 15 | I39: =G39*H39 -> 95.52 | J39: =IF(I39="","",I39*(1+Paramètres!$B$2)) -> 114.624 | K39: =I39*0.1 -> 9.552 | L39: =I39-K39-G39 -> 79.6 | M39: =L39/I39 -> 0.83333333 | O39: =IF(J39="","",ROUNDUP(J39+0.01,0)-0.01) -> 114.99 | P39: =IF(O39="","",O39/(1+Paramètres!$B$2)) -> 95.825 | Q39: =IF(P39="","",P39*0.1) -> 9.5825 | R39: 1
A40: BAC-39 | B40: Bâche qualité supérieure | C40: 150 × 100 cm | D40: 150 | E40: 100 | F40: =D40*E40/10000 -> 1.5 | G40: =(F40*1.2*4.24+F40*1.28) -> 9.552 | H40: =H39 -> 15 | I40: =G40*H40 -> 143.28 | J40: =IF(I40="","",I40*(1+Paramètres!$B$2)) -> 171.936 | K40: =I40*0.1 -> 14.328 | L40: =I40-K40-G40 -> 119.4 | M40: =L40/I40 -> 0.83333333 | O40: =IF(J40="","",ROUNDUP(J40+0.01,0)-0.01) -> 171.99 | P40: =IF(O40="","",O40/(1+Paramètres!$B$2)) -> 143.325 | Q40: =IF(P40="","",P40*0.1) -> 14.3325 | R40: 1
A41: BAC-40 | B41: Bâche qualité supérieure | C41: 200 × 100 cm | D41: 200 | E41: 100 | F41: =D41*E41/10000 -> 2 | G41: =(F41*1.2*4.24+F41*1.28) -> 12.736 | H41: =H40 -> 15 | I41: =G41*H41 -> 191.04 | J41: =IF(I41="","",I41*(1+Paramètres!$B$2)) -> 229.248 | K41: =I41*0.1 -> 19.104 | L41: =I41-K41-G41 -> 159.2 | M41: =L41/I41 -> 0.83333333 | O41: =IF(J41="","",ROUNDUP(J41+0.01,0)-0.01) -> 229.99 | P41: =IF(O41="","",O41/(1+Paramètres!$B$2)) -> 191.65833 | Q41: =IF(P41="","",P41*0.1) -> 19.165833 | R41: 1
A42: BAC-41 | B42: Bâche qualité supérieure | C42: 250 × 100 cm | D42: 250 | E42: 100 | F42: =D42*E42/10000 -> 2.5 | G42: =(F42*1.2*4.24+F42*1.28) -> 15.92 | H42: =H41 -> 15 | I42: =G42*H42 -> 238.8 | J42: =IF(I42="","",I42*(1+Paramètres!$B$2)) -> 286.56 | K42: =I42*0.1 -> 23.88 | L42: =I42-K42-G42 -> 199 | M42: =L42/I42 -> 0.83333333 | O42: =IF(J42="","",ROUNDUP(J42+0.01,0)-0.01) -> 286.99 | P42: =IF(O42="","",O42/(1+Paramètres!$B$2)) -> 239.15833 | Q42: =IF(P42="","",P42*0.1) -> 23.915833 | R42: 1
A43: BAC-42 | B43: Bâche qualité supérieure | C43: 300 × 100 cm | D43: 300 | E43: 100 | F43: =D43*E43/10000 -> 3 | G43: =(F43*1.2*4.24+F43*1.28) -> 19.104 | H43: =H42 -> 15 | I43: =G43*H43 -> 286.56 | J43: =IF(I43="","",I43*(1+Paramètres!$B$2)) -> 343.872 | K43: =I43*0.1 -> 28.656 | L43: =I43-K43-G43 -> 238.8 | M43: =L43/I43 -> 0.83333333 | O43: =IF(J43="","",ROUNDUP(J43+0.01,0)-0.01) -> 343.99 | P43: =IF(O43="","",O43/(1+Paramètres!$B$2)) -> 286.65833 | Q43: =IF(P43="","",P43*0.1) -> 28.665833 | R43: 1
A44: BAC-43 | B44: Bâche qualité supérieure | C44: 100 × 130 cm | D44: 100 | E44: 130 | F44: =D44*E44/10000 -> 1.3 | G44: =(F44*1.2*4.24+F44*1.28) -> 8.2784 | H44: =H43 -> 15 | I44: =G44*H44 -> 124.176 | J44: =IF(I44="","",I44*(1+Paramètres!$B$2)) -> 149.0112 | K44: =I44*0.1 -> 12.4176 | L44: =I44-K44-G44 -> 103.48 | M44: =L44/I44 -> 0.83333333 | O44: =IF(J44="","",ROUNDUP(J44+0.01,0)-0.01) -> 149.99 | P44: =IF(O44="","",O44/(1+Paramètres!$B$2)) -> 124.99167 | Q44: =IF(P44="","",P44*0.1) -> 12.499167 | R44: 1
A45: BAC-44 | B45: Bâche qualité supérieure | C45: 150 × 130 cm | D45: 150 | E45: 130 | F45: =D45*E45/10000 -> 1.95 | G45: =(F45*1.2*4.24+F45*1.28) -> 12.4176 | H45: =H44 -> 15 | I45: =G45*H45 -> 186.264 | J45: =IF(I45="","",I45*(1+Paramètres!$B$2)) -> 223.5168 | K45: =I45*0.1 -> 18.6264 | L45: =I45-K45-G45 -> 155.22 | M45: =L45/I45 -> 0.83333333 | O45: =IF(J45="","",ROUNDUP(J45+0.01,0)-0.01) -> 223.99 | P45: =IF(O45="","",O45/(1+Paramètres!$B$2)) -> 186.65833 | Q45: =IF(P45="","",P45*0.1) -> 18.665833 | R45: 1
A46: BAC-45 | B46: Bâche qualité supérieure | C46: 200 × 130 cm | D46: 200 | E46: 130 | F46: =D46*E46/10000 -> 2.6 | G46: =(F46*1.2*4.24+F46*1.28) -> 16.5568 | H46: =H45 -> 15 | I46: =G46*H46 -> 248.352 | J46: =IF(I46="","",I46*(1+Paramètres!$B$2)) -> 298.0224 | K46: =I46*0.1 -> 24.8352 | L46: =I46-K46-G46 -> 206.96 | M46: =L46/I46 -> 0.83333333 | O46: =IF(J46="","",ROUNDUP(J46+0.01,0)-0.01) -> 298.99 | P46: =IF(O46="","",O46/(1+Paramètres!$B$2)) -> 249.15833 | Q46: =IF(P46="","",P46*0.1) -> 24.915833 | R46: 1
A47: BAC-46 | B47: Bâche qualité supérieure | C47: 250 × 130 cm | D47: 250 | E47: 130 | F47: =D47*E47/10000 -> 3.25 | G47: =(F47*1.2*4.24+F47*1.28) -> 20.696 | H47: =H46 -> 15 | I47: =G47*H47 -> 310.44 | J47: =IF(I47="","",I47*(1+Paramètres!$B$2)) -> 372.528 | K47: =I47*0.1 -> 31.044 | L47: =I47-K47-G47 -> 258.7 | M47: =L47/I47 -> 0.83333333 | O47: =IF(J47="","",ROUNDUP(J47+0.01,0)-0.01) -> 372.99 | P47: =IF(O47="","",O47/(1+Paramètres!$B$2)) -> 310.825 | Q47: =IF(P47="","",P47*0.1) -> 31.0825 | R47: 1
... A52: BAC-51 | B52: Bâche qualité supérieure | C52: 300 × 150 cm | D52: 300 | E52: 150 | F52: =D52*E52/10000 -> 4.5 | G52: =(F52*1.2*4.24+F52*1.28) -> 28.656 | H52: =H51 -> 15 | I52: =G52*H52 -> 429.84 | J52: =IF(I52="","",I52*(1+Paramètres!$B$2)) -> 515.808 | K52: =I52*0.1 -> 42.984 | L52: =I52-K52-G52 -> 358.2 | M52: =L52/I52 -> 0.83333333 | O52: =IF(J52="","",ROUNDUP(J52+0.01,0)-0.01) -> 515.99 | P52: =IF(O52="","",O52/(1+Paramètres!$B$2)) -> 429.99167 | Q52: =IF(P52="","",P52*0.1) -> 42.999167 | R52: 1
A53: STK-01 | B53: Sticker brillant | C53: 5 cm (plus grand côté) | D53: 5 | E53: 5 | F53: =D53*E53/10000 -> 0.0025 | G53: =(F53*1.2*5.15+F53*1.28) -> 0.01865 | H53: 20 | I53: =G53*H53 -> 0.373 | J53: =IF(I53="","",I53*(1+Paramètres!$B$2)) -> 0.4476 | K53: =I53*0.1 -> 0.0373 | L53: =I53-K53-G53 -> 0.31705 | M53: =L53/I53 -> 0.85 | O53: 0.49 | P53: =IF(O53="","",O53/(1+Paramètres!$B$2)) -> 0.40833333 | Q53: =IF(P53="","",P53*0.1) -> 0.040833333 | R53: 5
A54: STK-02 | B54: Sticker brillant | C54: 10 cm (plus grand côté) | D54: 10 | E54: 10 | F54: =D54*E54/10000 -> 0.01 | G54: =(F54*1.2*5.15+F54*1.28) -> 0.0746 | H54: 20 | I54: =G54*H54 -> 1.492 | J54: =IF(I54="","",I54*(1+Paramètres!$B$2)) -> 1.7904 | K54: =I54*0.1 -> 0.1492 | L54: =I54-K54-G54 -> 1.2682 | M54: =L54/I54 -> 0.85 | O54: =IF(J54="","",ROUNDUP(J54+0.01,0)-0.01) -> 1.99 | P54: =IF(O54="","",O54/(1+Paramètres!$B$2)) -> 1.6583333 | Q54: =IF(P54="","",P54*0.1) -> 0.16583333 | R54: 1
A55: STK-03 | B55: Sticker brillant | C55: 20 cm (plus grand côté) | D55: 20 | E55: 20 | F55: =D55*E55/10000 -> 0.04 | G55: =(F55*1.2*5.15+F55*1.28) -> 0.2984 | H55: 15 | I55: =G55*H55 -> 4.476 | J55: =IF(I55="","",I55*(1+Paramètres!$B$2)) -> 5.3712 | K55: =I55*0.1 -> 0.4476 | L55: =I55-K55-G55 -> 3.73 | M55: =L55/I55 -> 0.83333333 | O55: =IF(J55="","",ROUNDUP(J55+0.01,0)-0.01) -> 5.99 | P55: =IF(O55="","",O55/(1+Paramètres!$B$2)) -> 4.9916667 | Q55: =IF(P55="","",P55*0.1) -> 0.49916667 | R55: 1
A56: STK-04 | B56: Sticker brillant | C56: 30 cm (plus grand côté) | D56: 30 | E56: 30 | F56: =D56*E56/10000 -> 0.09 | G56: =(F56*1.2*5.15+F56*1.28) -> 0.6714 | H56: =H55 -> 15 | I56: =G56*H56 -> 10.071 | J56: =IF(I56="","",I56*(1+Paramètres!$B$2)) -> 12.0852 | K56: =I56*0.1 -> 1.0071 | L56: =I56-K56-G56 -> 8.3925 | M56: =L56/I56 -> 0.83333333 | O56: =IF(J56="","",ROUNDUP(J56+0.01,0)-0.01) -> 12.99 | P56: =IF(O56="","",O56/(1+Paramètres!$B$2)) -> 10.825 | Q56: =IF(P56="","",P56*0.1) -> 1.0825 | R56: 1
A57: STK-05 | B57: Sticker brillant | C57: 40 cm (plus grand côté) | D57: 40 | E57: 40 | F57: =D57*E57/10000 -> 0.16 | G57: =(F57*1.2*5.15+F57*1.28) -> 1.1936 | H57: =H56 -> 15 | I57: =G57*H57 -> 17.904 | J57: =IF(I57="","",I57*(1+Paramètres!$B$2)) -> 21.4848 | K57: =I57*0.1 -> 1.7904 | L57: =I57-K57-G57 -> 14.92 | M57: =L57/I57 -> 0.83333333 | O57: =IF(J57="","",ROUNDUP(J57+0.01,0)-0.01) -> 21.99 | P57: =IF(O57="","",O57/(1+Paramètres!$B$2)) -> 18.325 | Q57: =IF(P57="","",P57*0.1) -> 1.8325 | R57: 1
A58: STK-06 | B58: Sticker brillant | C58: 60 cm (plus grand côté) | D58: 60 | E58: 60 | F58: =D58*E58/10000 -> 0.36 | G58: =(F58*1.2*5.15+F58*1.28) -> 2.6856 | H58: =H57 -> 15 | I58: =G58*H58 -> 40.284 | J58: =IF(I58="","",I58*(1+Paramètres!$B$2)) -> 48.3408 | K58: =I58*0.1 -> 4.0284 | L58: =I58-K58-G58 -> 33.57 | M58: =L58/I58 -> 0.83333333 | O58: =IF(J58="","",ROUNDUP(J58+0.01,0)-0.01) -> 48.99 | P58: =IF(O58="","",O58/(1+Paramètres!$B$2)) -> 40.825 | Q58: =IF(P58="","",P58*0.1) -> 4.0825 | R58: 1
A59: STK-07 | B59: Sticker mat | C59: 5 cm (plus grand côté) | D59: 5 | E59: 5 | F59: =D59*E59/10000 -> 0.0025 | G59: =(F59*1.2*5.15+F59*1.28) -> 0.01865 | H59: =H58 -> 15 | I59: =G59*H59 -> 0.27975 | J59: =IF(I59="","",I59*(1+Paramètres!$B$2)) -> 0.3357 | K59: =I59*0.1 -> 0.027975 | L59: =I59-K59-G59 -> 0.233125 | M59: =L59/I59 -> 0.83333333 | O59: 0.49 | P59: =IF(O59="","",O59/(1+Paramètres!$B$2)) -> 0.40833333 | Q59: =IF(P59="","",P59*0.1) -> 0.040833333 | R59: 5
A60: STK-08 | B60: Sticker mat | C60: 10 cm (plus grand côté) | D60: 10 | E60: 10 | F60: =D60*E60/10000 -> 0.01 | G60: =(F60*1.2*5.15+F60*1.28) -> 0.0746 | H60: 20 | I60: =G60*H60 -> 1.492 | J60: =IF(I60="","",I60*(1+Paramètres!$B$2)) -> 1.7904 | K60: =I60*0.1 -> 0.1492 | L60: =I60-K60-G60 -> 1.2682 | M60: =L60/I60 -> 0.85 | O60: =IF(J60="","",ROUNDUP(J60+0.01,0)-0.01) -> 1.99 | P60: =IF(O60="","",O60/(1+Paramètres!$B$2)) -> 1.6583333 | Q60: =IF(P60="","",P60*0.1) -> 0.16583333 | R60: 1
A61: STK-09 | B61: Sticker mat | C61: 20 cm (plus grand côté) | D61: 20 | E61: 20 | F61: =D61*E61/10000 -> 0.04 | G61: =(F61*1.2*5.15+F61*1.28) -> 0.2984 | H61: 20 | I61: =G61*H61 -> 5.968 | J61: =IF(I61="","",I61*(1+Paramètres!$B$2)) -> 7.1616 | K61: =I61*0.1 -> 0.5968 | L61: =I61-K61-G61 -> 5.0728 | M61: =L61/I61 -> 0.85 | O61: =IF(J61="","",ROUNDUP(J61+0.01,0)-0.01) -> 7.99 | P61: =IF(O61="","",O61/(1+Paramètres!$B$2)) -> 6.6583333 | Q61: =IF(P61="","",P61*0.1) -> 0.66583333 | R61: 1
A62: STK-10 | B62: Sticker mat | C62: 30 cm (plus grand côté) | D62: 30 | E62: 30 | F62: =D62*E62/10000 -> 0.09 | G62: =(F62*1.2*5.15+F62*1.28) -> 0.6714 | H62: 15 | I62: =G62*H62 -> 10.071 | J62: =IF(I62="","",I62*(1+Paramètres!$B$2)) -> 12.0852 | K62: =I62*0.1 -> 1.0071 | L62: =I62-K62-G62 -> 8.3925 | M62: =L62/I62 -> 0.83333333 | O62: =IF(J62="","",ROUNDUP(J62+0.01,0)-0.01) -> 12.99 | P62: =IF(O62="","",O62/(1+Paramètres!$B$2)) -> 10.825 | Q62: =IF(P62="","",P62*0.1) -> 1.0825 | R62: 1
A63: STK-11 | B63: Sticker mat | C63: 40 cm (plus grand côté) | D63: 40 | E63: 40 | F63: =D63*E63/10000 -> 0.16 | G63: =(F63*1.2*5.15+F63*1.28) -> 1.1936 | H63: =H62 -> 15 | I63: =G63*H63 -> 17.904 | J63: =IF(I63="","",I63*(1+Paramètres!$B$2)) -> 21.4848 | K63: =I63*0.1 -> 1.7904 | L63: =I63-K63-G63 -> 14.92 | M63: =L63/I63 -> 0.83333333 | O63: =IF(J63="","",ROUNDUP(J63+0.01,0)-0.01) -> 21.99 | P63: =IF(O63="","",O63/(1+Paramètres!$B$2)) -> 18.325 | Q63: =IF(P63="","",P63*0.1) -> 1.8325 | R63: 1
A64: STK-12 | B64: Sticker mat | C64: 60 cm (plus grand côté) | D64: 60 | E64: 60 | F64: =D64*E64/10000 -> 0.36 | G64: =(F64*1.2*5.15+F64*1.28) -> 2.6856 | H64: =H63 -> 15 | I64: =G64*H64 -> 40.284 | J64: =IF(I64="","",I64*(1+Paramètres!$B$2)) -> 48.3408 | K64: =I64*0.1 -> 4.0284 | L64: =I64-K64-G64 -> 33.57 | M64: =L64/I64 -> 0.83333333 | O64: =IF(J64="","",ROUNDUP(J64+0.01,0)-0.01) -> 48.99 | P64: =IF(O64="","",O64/(1+Paramètres!$B$2)) -> 40.825 | Q64: =IF(P64="","",P64*0.1) -> 4.0825 | R64: 1
A65: MAG-01 | B65: Magnet mat | C65: 5 cm (plus grand côté) | D65: 5 | E65: 5 | F65: =D65*E65/10000 -> 0.0025 | G65: =(F65*1.2*6.5+F65*1.28) -> 0.0227 | H65: =H64 -> 15 | I65: =G65*H65 -> 0.3405 | J65: =IF(I65="","",I65*(1+Paramètres!$B$2)) -> 0.4086 | K65: =I65*0.1 -> 0.03405 | L65: =I65-K65-G65 -> 0.28375 | M65: =L65/I65 -> 0.83333333 | O65: =IF(J65="","",ROUNDUP(J65+0.01,0)-0.01) -> 0.99 | P65: =IF(O65="","",O65/(1+Paramètres!$B$2)) -> 0.825 | Q65: =IF(P65="","",P65*0.1) -> 0.0825 | R65: 1
A66: MAG-02 | B66: Magnet mat | C66: 10 cm (plus grand côté) | D66: 10 | E66: 10 | F66: =D66*E66/10000 -> 0.01 | G66: =(F66*1.2*6.5+F66*1.28) -> 0.0908 | H66: =H65 -> 15 | I66: =G66*H66 -> 1.362 | J66: =IF(I66="","",I66*(1+Paramètres!$B$2)) -> 1.6344 | K66: =I66*0.1 -> 0.1362 | L66: =I66-K66-G66 -> 1.135 | M66: =L66/I66 -> 0.83333333 | O66: =IF(J66="","",ROUNDUP(J66+0.01,0)-0.01) -> 1.99 | P66: =IF(O66="","",O66/(1+Paramètres!$B$2)) -> 1.6583333 | Q66: =IF(P66="","",P66*0.1) -> 0.16583333 | R66: 1
A67: MAG-03 | B67: Magnet mat | C67: 20 cm (plus grand côté) | D67: 20 | E67: 20 | F67: =D67*E67/10000 -> 0.04 | G67: =(F67*1.2*6.5+F67*1.28) -> 0.3632 | H67: =H66 -> 15 | I67: =G67*H67 -> 5.448 | J67: =IF(I67="","",I67*(1+Paramètres!$B$2)) -> 6.5376 | K67: =I67*0.1 -> 0.5448 | L67: =I67-K67-G67 -> 4.54 | M67: =L67/I67 -> 0.83333333 | O67: =IF(J67="","",ROUNDUP(J67+0.01,0)-0.01) -> 6.99 | P67: =IF(O67="","",O67/(1+Paramètres!$B$2)) -> 5.825 | Q67: =IF(P67="","",P67*0.1) -> 0.5825 | R67: 1
A68: MAG-04 | B68: Magnet mat | C68: 30 cm (plus grand côté) | D68: 30 | E68: 30 | F68: =D68*E68/10000 -> 0.09 | G68: =(F68*1.2*6.5+F68*1.28) -> 0.8172 | H68: =H67 -> 15 | I68: =G68*H68 -> 12.258 | J68: =IF(I68="","",I68*(1+Paramètres!$B$2)) -> 14.7096 | K68: =I68*0.1 -> 1.2258 | L68: =I68-K68-G68 -> 10.215 | M68: =L68/I68 -> 0.83333333 | O68: =IF(J68="","",ROUNDUP(J68+0.01,0)-0.01) -> 14.99 | P68: =IF(O68="","",O68/(1+Paramètres!$B$2)) -> 12.491667 | Q68: =IF(P68="","",P68*0.1) -> 1.2491667 | R68: 1
A69: MAG-05 | B69: Magnet mat | C69: 40 cm (plus grand côté) | D69: 40 | E69: 40 | F69: =D69*E69/10000 -> 0.16 | G69: =(F69*1.2*6.5+F69*1.28) -> 1.4528 | H69: =H68 -> 15 | I69: =G69*H69 -> 21.792 | J69: =IF(I69="","",I69*(1+Paramètres!$B$2)) -> 26.1504 | K69: =I69*0.1 -> 2.1792 | L69: =I69-K69-G69 -> 18.16 | M69: =L69/I69 -> 0.83333333 | O69: =IF(J69="","",ROUNDUP(J69+0.01,0)-0.01) -> 26.99 | P69: =IF(O69="","",O69/(1+Paramètres!$B$2)) -> 22.491667 | Q69: =IF(P69="","",P69*0.1) -> 2.2491667 | R69: 1
A70: MAG-06 | B70: Magnet mat | C70: 60 cm (plus grand côté) | D70: 60 | E70: 60 | F70: =D70*E70/10000 -> 0.36 | G70: =(F70*1.2*6.5+F70*1.28) -> 3.2688 | H70: =H69 -> 15 | I70: =G70*H70 -> 49.032 | J70: =IF(I70="","",I70*(1+Paramètres!$B$2)) -> 58.8384 | K70: =I70*0.1 -> 4.9032 | L70: =I70-K70-G70 -> 40.86 | M70: =L70/I70 -> 0.83333333 | O70: =IF(J70="","",ROUNDUP(J70+0.01,0)-0.01) -> 58.99 | P70: =IF(O70="","",O70/(1+Paramètres!$B$2)) -> 49.158333 | Q70: =IF(P70="","",P70*0.1) -> 4.9158333 | R70: 1
A71: POS-01 | B71: Poster | C71: A3 | D71: 29.7 | E71: 42 | F71: =D71*E71/10000 -> 0.12474 | G71: =(F71*1.3*0.81+F71*1.28) -> 0.29101842 | H71: 20 | I71: =G71*H71 -> 5.8203684 | J71: =IF(I71="","",I71*(1+Paramètres!$B$2)) -> 6.9844421 | K71: =I71*0.1 -> 0.58203684 | L71: =I71-K71-G71 -> 4.9473131 | M71: =L71/I71 -> 0.85 | O71: =IF(J71="","",ROUNDUP(J71+0.01,0)-0.01) -> 6.99 | P71: =IF(O71="","",O71/(1+Paramètres!$B$2)) -> 5.825 | Q71: =IF(P71="","",P71*0.1) -> 0.5825 | R71: 1
A72: POS-02 | B72: Poster | C72: A2 | D72: 42 | E72: 59.4 | F72: =D72*E72/10000 -> 0.24948 | G72: =(F72*1.3*0.81+F72*1.28) -> 0.58203684 | H72: 20 | I72: =G72*H72 -> 11.640737 | J72: =IF(I72="","",I72*(1+Paramètres!$B$2)) -> 13.968884 | K72: =I72*0.1 -> 1.1640737 | L72: =I72-K72-G72 -> 9.8946263 | M72: =L72/I72 -> 0.85 | O72: =IF(J72="","",ROUNDUP(J72+0.01,0)-0.01) -> 13.99 | P72: =IF(O72="","",O72/(1+Paramètres!$B$2)) -> 11.658333 | Q72: =IF(P72="","",P72*0.1) -> 1.1658333 | R72: 1
A73: POS-04 | B73: Poster | C73: 40 × 60 cm | D73: 40 | E73: 60 | F73: =D73*E73/10000 -> 0.24 | G73: =(F73*1.3*0.81+F73*1.28) -> 0.55992 | H73: 15 | I73: =G73*H73 -> 8.3988 | J73: =IF(I73="","",I73*(1+Paramètres!$B$2)) -> 10.07856 | K73: =I73*0.1 -> 0.83988 | L73: =I73-K73-G73 -> 6.999 | M73: =L73/I73 -> 0.83333333 | O73: =IF(J73="","",ROUNDUP(J73+0.01,0)-0.01) -> 10.99 | P73: =IF(O73="","",O73/(1+Paramètres!$B$2)) -> 9.1583333 | Q73: =IF(P73="","",P73*0.1) -> 0.91583333 | R73: 1
A74: POS-03 | B74: Poster | C74: 50 × 70 cm | D74: 50 | E74: 70 | F74: =D74*E74/10000 -> 0.35 | G74: =(F74*1.3*0.81+F74*1.28) -> 0.81655 | H74: =H73 -> 15 | I74: =G74*H74 -> 12.24825 | J74: =IF(I74="","",I74*(1+Paramètres!$B$2)) -> 14.6979 | K74: =I74*0.1 -> 1.224825 | L74: =I74-K74-G74 -> 10.206875 | M74: =L74/I74 -> 0.83333333 | O74: =IF(J74="","",ROUNDUP(J74+0.01,0)-0.01) -> 14.99 | P74: =IF(O74="","",O74/(1+Paramètres!$B$2)) -> 12.491667 | Q74: =IF(P74="","",P74*0.1) -> 1.2491667 | R74: 1
A75: POS-05 | B75: Poster | C75: 60 × 90 cm | D75: 60 | E75: 90 | F75: =D75*E75/10000 -> 0.54 | G75: =(F75*1.3*0.81+F75*1.28) -> 1.25982 | H75: =H74 -> 15 | I75: =G75*H75 -> 18.8973 | J75: =IF(I75="","",I75*(1+Paramètres!$B$2)) -> 22.67676 | K75: =I75*0.1 -> 1.88973 | L75: =I75-K75-G75 -> 15.74775 | M75: =L75/I75 -> 0.83333333 | O75: =IF(J75="","",ROUNDUP(J75+0.01,0)-0.01) -> 22.99 | P75: =IF(O75="","",O75/(1+Paramètres!$B$2)) -> 19.158333 | Q75: =IF(P75="","",P75*0.1) -> 1.9158333 | R75: 1
A76: ALU-01 | B76: Tableau alu (Dibond) | C76: 20 x 20 cm | D76: 20 | E76: 20 | F76: =D76*E76/10000 -> 0.04 | G76: =(F76*1.2*10.5+F76*1.35+F76*2) -> 0.638 | H76: 20 | I76: =G76*H76 -> 12.76 | J76: =IF(I76="","",I76*(1+Paramètres!$B$2)) -> 15.312 | K76: =I76*0.1 -> 1.276 | L76: =I76-K76-G76 -> 10.846 | M76: =L76/I76 -> 0.85 | O76: =IF(J76="","",ROUNDUP(J76+0.01,0)-0.01) -> 15.99 | P76: =IF(O76="","",O76/(1+Paramètres!$B$2)) -> 13.325 | Q76: =IF(P76="","",P76*0.1) -> 1.3325 | R76: 1
A77: ALU-02 | B77: Tableau alu (Dibond) | C77: 20 x 30 cm | D77: 20 | E77: 30 | F77: =D77*E77/10000 -> 0.06 | G77: =(F77*1.2*10.5+F77*1.35+F77*2) -> 0.957 | H77: =H76 -> 20 | I77: =G77*H77 -> 19.14 | J77: =IF(I77="","",I77*(1+Paramètres!$B$2)) -> 22.968 | K77: =I77*0.1 -> 1.914 | L77: =I77-K77-G77 -> 16.269 | M77: =L77/I77 -> 0.85 | O77: =IF(J77="","",ROUNDUP(J77+0.01,0)-0.01) -> 22.99 | P77: =IF(O77="","",O77/(1+Paramètres!$B$2)) -> 19.158333 | Q77: =IF(P77="","",P77*0.1) -> 1.9158333 | R77: 1
A78: ALU-03 | B78: Tableau alu (Dibond) | C78: 30 × 40 cm | D78: 30 | E78: 40 | F78: =D78*E78/10000 -> 0.12 | G78: =(F78*1.2*10.5+F78*1.35+F78*2) -> 1.914 | H78: 15 | I78: =G78*H78 -> 28.71 | J78: =IF(I78="","",I78*(1+Paramètres!$B$2)) -> 34.452 | K78: =I78*0.1 -> 2.871 | L78: =I78-K78-G78 -> 23.925 | M78: =L78/I78 -> 0.83333333 | O78: =IF(J78="","",ROUNDUP(J78+0.01,0)-0.01) -> 34.99 | P78: =IF(O78="","",O78/(1+Paramètres!$B$2)) -> 29.158333 | Q78: =IF(P78="","",P78*0.1) -> 2.9158333 | R78: 1
A79: ALU-04 | B79: Tableau alu (Dibond) | C79: 40 × 60 cm | D79: 40 | E79: 60 | F79: =D79*E79/10000 -> 0.24 | G79: =(F79*1.2*10.5+F79*1.35+F79*2) -> 3.828 | H79: =H78 -> 15 | I79: =G79*H79 -> 57.42 | J79: =IF(I79="","",I79*(1+Paramètres!$B$2)) -> 68.904 | K79: =I79*0.1 -> 5.742 | L79: =I79-K79-G79 -> 47.85 | M79: =L79/I79 -> 0.83333333 | O79: =IF(J79="","",ROUNDUP(J79+0.01,0)-0.01) -> 68.99 | P79: =IF(O79="","",O79/(1+Paramètres!$B$2)) -> 57.491667 | Q79: =IF(P79="","",P79*0.1) -> 5.7491667 | R79: 1
A80: ALU-05 | B80: Tableau alu (Dibond) | C80: 60 × 90 cm | D80: 60 | E80: 90 | F80: =D80*E80/10000 -> 0.54 | G80: =(F80*1.2*10.5+F80*1.35+F80*2) -> 8.613 | H80: =H79 -> 15 | I80: =G80*H80 -> 129.195 | J80: =IF(I80="","",I80*(1+Paramètres!$B$2)) -> 155.034 | K80: =I80*0.1 -> 12.9195 | L80: =I80-K80-G80 -> 107.6625 | M80: =L80/I80 -> 0.83333333 | O80: =IF(J80="","",ROUNDUP(J80+0.01,0)-0.01) -> 155.99 | P80: =IF(O80="","",O80/(1+Paramètres!$B$2)) -> 129.99167 | Q80: =IF(P80="","",P80*0.1) -> 12.999167 | R80: 1
A81: ALU-06 | B81: Tableau alu (Dibond) | C81: 80 × 120 cm | D81: 80 | E81: 120 | F81: =D81*E81/10000 -> 0.96 | G81: =(F81*1.2*10.5+F81*1.35+F81*2) -> 15.312 | H81: =H80 -> 15 | I81: =G81*H81 -> 229.68 | J81: =IF(I81="","",I81*(1+Paramètres!$B$2)) -> 275.616 | K81: =I81*0.1 -> 22.968 | L81: =I81-K81-G81 -> 191.4 | M81: =L81/I81 -> 0.83333333 | O81: =IF(J81="","",ROUNDUP(J81+0.01,0)-0.01) -> 275.99 | P81: =IF(O81="","",O81/(1+Paramètres!$B$2)) -> 229.99167 | Q81: =IF(P81="","",P81*0.1) -> 22.999167 | R81: 1
A82: ALU-07 | B82: Tableau alu (Dibond) | C82: 100 × 150 cm | D82: 100 | E82: 150 | F82: =D82*E82/10000 -> 1.5 | G82: =(F82*1.2*10.5+F82*1.35+F82*2) -> 23.925 | H82: =H81 -> 15 | I82: =G82*H82 -> 358.875 | J82: =IF(I82="","",I82*(1+Paramètres!$B$2)) -> 430.65 | K82: =I82*0.1 -> 35.8875 | L82: =I82-K82-G82 -> 299.0625 | M82: =L82/I82 -> 0.83333333 | O82: =IF(J82="","",ROUNDUP(J82+0.01,0)-0.01) -> 430.99 | P82: =IF(O82="","",O82/(1+Paramètres!$B$2)) -> 359.15833 | Q82: =IF(P82="","",P82*0.1) -> 35.915833 | R82: 1
A84: Sticker : dimensions = plus grand côté ; la découpe à la forme est une finition (onglet Finitions).

Sheet Paramètres
A1: Paramètre | B1: Valeur
A2: Taux de TVA | B2: 0.2 | C2: Hypothèse : TVA française 20 % (ventes UE via OSS à traiter à part)

Sheet Finitions
A1: Support | B1: Reference | D1: Finition | E1: Type | F1: Supplément HT (€)
A2: Bâche | D2: Œillets | E2: Oeuillets aluminium | F2: 4.5
A3: Bâche | D3: Tendeur crochet | E3: Tendeur crochet | F3: 7.5
A4: Tableau alu (Dibond) | B4: frame.board_châssis.15 | C4: 20 x 20 cm | D4: Système d'accroche au dos | E4: Barres aluminium | F4: 10
A5: Tableau alu (Dibond) | B5: frame.board_châssis.16 | C5: 20 x 30 cm | D5: Système d'accroche au dos | E5: Barres aluminium | F5: 10
A6: Tableau alu (Dibond) | B6: frame.board_châssis.17 | C6: 30 × 40 cm | D6: Système d'accroche au dos | E6: Barres aluminium | F6: 10
A7: Tableau alu (Dibond) | B7: frame.board_châssis.18 | C7: 40 × 60 cm | D7: Système d'accroche au dos | E7: Barres aluminium | F7: 15
A8: Tableau alu (Dibond) | B8: frame.board_châssis.19 | C8: 60 × 90 cm | D8: Système d'accroche au dos | E8: Barres aluminium | F8: 15
A9: Tableau alu (Dibond) | B9: frame.board_châssis.20 | C9: 80 × 120 cm | D9: Système d'accroche au dos | E9: Barres aluminium | F9: 15
A10: Tableau alu (Dibond) | B10: frame.board_châssis.21 | C10: 100 × 150 cm | D10: Système d'accroche au dos | E10: Barres aluminium | F10: 15
A11: Tableau alu (Dibond) | B11: ALU-01frame.board_L25 - BLANC | C11: 20 x 20 cm | D11: Cadre aluminium blanc | F11: 15
A12: Tableau alu (Dibond) | B12: ALU-01frame.board_L25 - BLANC | C12: 20 x 30 cm | D12: Cadre aluminium blanc | F12: 15
A13: Tableau alu (Dibond) | B13: ALU-01frame.board_L25 - BLANC | C13: 30 × 40 cm | D13: Cadre aluminium blanc | F13: 15
A14: Tableau alu (Dibond) | B14: ALU-01frame.board_L25 - BLANC | C14: 40 × 60 cm | D14: Cadre aluminium blanc | F14: 15
A15: Tableau alu (Dibond) | B15: ALU-01frame.board_L25 - BLANC | C15: 60 × 90 cm | D15: Cadre aluminium blanc | F15: 15
A16: Tableau alu (Dibond) | B16: ALU-01frame.board_L25 - BLANC | C16: 80 × 120 cm | D16: Cadre aluminium blanc | F16: 15
A17: Tableau alu (Dibond) | B17: ALU-01frame.board_L25 - BLANC | C17: 100 × 150 cm | D17: Cadre aluminium blanc | F17: 15
A18: Tableau alu (Dibond) | B18: ALU-01frame.board_L25 - NOIR | C18: 20 x 20 cm | D18: Cadre aluminium noir | F18: 15
A19: Tableau alu (Dibond) | B19: ALU-01frame.board_L25 - NOIR | C19: 20 x 30 cm | D19: Cadre aluminium noir | F19: 15
A20: Tableau alu (Dibond) | B20: ALU-01frame.board_L25 - NOIR | C20: 30 × 40 cm | D20: Cadre aluminium noir | F20: 15
A21: Tableau alu (Dibond) | B21: ALU-01frame.board_L25 - NOIR | C21: 40 × 60 cm | D21: Cadre aluminium noir | F21: 15
A22: Tableau alu (Dibond) | B22: ALU-01frame.board_L25 - NOIR | C22: 60 × 90 cm | D22: Cadre aluminium noir | F22: 15
... A24: Tableau alu (Dibond) | B24: ALU-01frame.board_L25 - NOIR | C24: 100 × 150 cm | D24: Cadre aluminium noir | F24: 15
